[{"text":"viaje espiritual","display":null,"type":"topic","weight":0.009},{"text":"vida ashram","display":null,"type":"topic","weight":0.004},{"text":"vida de lahiri mahasaya","display":null,"type":"topic","weight":0.003},{"text":"visión mística","display":null,"type":"topic","weight":0.003},{"text":"vida familiar","display":null,"type":"topic","weight":0.002},{"text":"vida monástica","display":null,"type":"topic","weight":0.002},{"text":"visiones espirituales","display":null,"type":"topic","weight":0.002},{"text":"visión espiritual","display":null,"type":"topic","weight":0.002},{"text":"viajes espirituales","display":null,"type":"topic","weight":0.002},{"text":"vida estudiantil","display":null,"type":"topic","weight":0.002},{"text":"vida de yogananda","display":null,"type":"topic","weight":0.002},{"text":"Visitamos Cachemira","display":null,"type":"chapter","weight":0.001}]