[{"text":"maya","display":"Maya — Cosmic illusion; the veil that makes the One appear as many.","type":"sanskrit","weight":0.339},{"text":"mantra","display":"Mantra — Sacred word or phrase used in meditation and devotion.","type":"sanskrit","weight":0.339},{"text":"Master Mahasaya","display":"Master Mahasaya — Author of The Gospel of Sri Ramakrishna. Mentioned in Autobiography.","type":"entity","weight":0.071},{"text":"Master Mahasaya on guru-disciple relationship","display":null,"type":"scoped","weight":0.027},{"text":"Master Mahasaya on divine mother","display":null,"type":"scoped","weight":0.017},{"text":"materialization","display":null,"type":"topic","weight":0.01},{"text":"maya and illusion","display":null,"type":"topic","weight":0.007},{"text":"maya and duality","display":null,"type":"topic","weight":0.007},{"text":"Materializing a Palace in the Himalayas","display":null,"type":"chapter","weight":0.003},{"text":"Mahavatar Babaji","display":"Mahavatar Babaji — Deathless guru. Revived and transmitted Kriya Yoga to Lahiri Mahasaya.","type":"entity","weight":0},{"text":"Mahatma Gandhi","display":"Mahatma Gandhi — Leader of Indian independence. Yogananda met him at Wardha ashram.","type":"entity","weight":0}]